core_services-0.1.0.dist-info/licenses/LICENSE
migrations/__init__.py
services/__init__.py
services/custom_service.py
core_services-0.1.0.dist-info/METADATA
core_services-0.1.0.dist-info/WHEEL
core_services-0.1.0.dist-info/top_level.txt
core_services-0.1.0.dist-info/RECORD
