Metadata-Version: 2.4
Name: core-services
Version: 0.1.0
Summary: Reusable service layer for Django apps
Author: Fodor Robert Stefan
Author-email: robifodor1234576@yahoo.com
License: MIT
Classifier: Framework :: Django
Classifier: Programming Language :: Python :: 3
License-File: LICENSE
Requires-Dist: Django>=3.2
Dynamic: author
Dynamic: author-email
Dynamic: classifier
Dynamic: license
Dynamic: license-file
Dynamic: requires-dist
Dynamic: summary
